SpaceTimeComplex
